Metadata-Version: 1.1
Name: aiio
Version: 0.1.1
Summary: english-speaking chat ai
Home-page: UNKNOWN
Author: Mario Balibrera
Author-email: mario.balibrera@gmail.com
License: MIT License
Platform: UNKNOWN
Classifier: Development Status :: 3 - Alpha
Classifier: Environment :: Console
Classifier: Intended Audience :: Developers
Classifier: License :: OSI Approved :: MIT License
Classifier: Operating System :: OS Independent
Classifier: Programming Language :: Python
Classifier: Topic :: Software Development :: Libraries :: Python Modules
